MensajesPruebaRene-6.0.data/scripts/test.py
mensajes/__init__.py
mensajes/adios/__init__.py
mensajes/adios/despedidas.py
MensajesPruebaRene-6.0.dist-info/LICENSE
MensajesPruebaRene-6.0.dist-info/METADATA
MensajesPruebaRene-6.0.dist-info/WHEEL
MensajesPruebaRene-6.0.dist-info/top_level.txt
MensajesPruebaRene-6.0.dist-info/RECORD
