Metadata-Version: 2.1
Name: MensajesPruebaRene
Version: 6.0
Summary: Un paquete para mandar saludos y despedidas
Home-page: https://www.renehdez.com
Author: Rene Hernandez
Author-email: renescanner97@gmail.com
Classifier: Environment :: Console
Classifier: Intended Audience :: Developers
Classifier: License :: OSI Approved :: MIT License
License-File: LICENSE
Requires-Dist: numpy >=1.26.4
